AUTHORS
LICENSE
MANIFEST.in
README.rst
setup.py
rapidsms_xray.egg-info/PKG-INFO
rapidsms_xray.egg-info/SOURCES.txt
rapidsms_xray.egg-info/dependency_links.txt
rapidsms_xray.egg-info/not-zip-safe
rapidsms_xray.egg-info/requires.txt
rapidsms_xray.egg-info/top_level.txt
xray/__init__.py
xray/app.py
xray/context_processors.py
xray/decorators.py
xray/events.py
xray/identity.py
xray/listeners.py
xray/models.py
xray/rolodex.py
xray/urls.py
xray/views.py
xray/static/xray/stylesheets/xray.css
xray/templates/xray/events_data.html
xray/templates/xray/events_form.html
xray/templates/xray/experiments.html
xray/templates/xray/index.html
xray/templatetags/__init__.py
xray/templatetags/xray_tags.py
xray/tests/__init__.py
xray/tests/base.py
xray/tests/headers.py
xray/tests/rolodex.py