Metadata-Version: 1.1
Name: rapidsms-xray
Version: 0.5.6b0
Summary: RapidSMS app for web and SMS split test experiments & event tracking.
Home-page: https://github.com/ewheeler/rapidsms-xray/
Author: Evan Wheeler
Author-email: evan@leapfrog.io
License: BSD
Platform: UNKNOWN
Classifier: Topic :: Internet :: WWW/HTTP :: Dynamic Content
Classifier: Intended Audience :: Developers
Classifier: License :: OSI Approved :: BSD License
Classifier: Programming Language :: Python
Classifier: Programming Language :: Python :: 2.6
Classifier: Programming Language :: Python :: 2.7
Classifier: Framework :: Django
Classifier: Development Status :: 4 - Beta
Classifier: Operating System :: OS Independent
